{"version":2,"kind":"Notebook","sha256":"af6e78a13f508b8b32de9cb6e2b797787fd2b0c544d4e70c969782f2082f9f88","slug":"notebooks.example-workflows.cneos-fireball","location":"/notebooks/example-workflows/cneos-fireball.ipynb","dependencies":[],"frontmatter":{"title":"NASA API: World Map of Fireball Impacts","content_includes_title":true,"kernelspec":{"name":"python3","display_name":"Python 3 (ipykernel)","language":"python"},"authors":[{"nameParsed":{"literal":"Project Pythia Community","given":"Project Pythia","family":"Community"},"name":"Project Pythia Community","url":"https://projectpythia.org/","id":"contributors-myst-generated-uid-0"}],"open_access":true,"license":{"content":{"id":"Apache-2.0","url":"https://opensource.org/licenses/Apache-2.0","name":"Apache License 2.0","free":true,"osi":true},"code":{"id":"CC-BY-4.0","url":"https://creativecommons.org/licenses/by/4.0/","name":"Creative Commons Attribution 4.0 International","free":true,"CC":true}},"github":"https://github.com/projectpythia/api-cookbook","copyright":"2024","numbering":{"title":{"offset":1}},"edit_url":"https://github.com/projectpythia/api-cookbook/blob/main/notebooks/example-workflows/cneos-fireball.ipynb","thumbnail":"/api-cookbook/build/22ccf97c98df98a0886e7227e136ac12.gif","exports":[{"format":"ipynb","filename":"cneos-fireball.ipynb","url":"/api-cookbook/build/cneos-fireball-e29965f197b8ce957ba16246dec831c9.ipynb"}]},"widgets":{},"mdast":{"type":"root","children":[{"type":"block","kind":"notebook-content","children":[{"type":"paragraph","position":{"start":{"line":1,"column":1},"end":{"line":1,"column":1}},"children":[{"type":"image","url":"/api-cookbook/build/22ccf97c98df98a0886e7227e136ac12.gif","alt":"Bay Area Fireball","key":"d17cAib5o7","urlSource":"https://www.nasa.gov/wp-content/uploads/2023/03/704419main_meteor-gif-full_full.gif?w=1041"}],"key":"xqzxrnt4Di"},{"type":"paragraph","position":{"start":{"line":3,"column":1},"end":{"line":3,"column":1}},"children":[{"type":"link","url":"https://www.nasa.gov/image-article/bay-area-fireball-oct-17-2012/","position":{"start":{"line":3,"column":1},"end":{"line":3,"column":1}},"children":[{"type":"text","value":"Bay Area Fireball, October 17, 2012","position":{"start":{"line":3,"column":1},"end":{"line":3,"column":1}},"key":"UEzFQQonUh"}],"urlSource":"https://www.nasa.gov/image-article/bay-area-fireball-oct-17-2012/","key":"oXTHwWHmub"}],"key":"VjqK5SCbmO"}],"key":"QDxxzy8Yjh"},{"type":"block","kind":"notebook-content","children":[{"type":"heading","depth":1,"position":{"start":{"line":1,"column":1},"end":{"line":1,"column":1}},"children":[{"type":"text","value":"NASA API: World Map of Fireball Impacts","position":{"start":{"line":1,"column":1},"end":{"line":1,"column":1}},"key":"S72s68byE8"}],"identifier":"nasa-api-world-map-of-fireball-impacts","label":"NASA API: World Map of Fireball Impacts","html_id":"nasa-api-world-map-of-fireball-impacts","implicit":true,"key":"fznaxXTqUV"}],"key":"bafH59iqwx"},{"type":"block","kind":"notebook-content","children":[{"type":"thematicBreak","position":{"start":{"line":1,"column":1},"end":{"line":1,"column":1}},"key":"GBnmUwK37u"}],"key":"s5f7sh4swy"},{"type":"block","kind":"notebook-content","children":[{"type":"heading","depth":2,"position":{"start":{"line":1,"column":1},"end":{"line":1,"column":1}},"children":[{"type":"text","value":"Overview","position":{"start":{"line":1,"column":1},"end":{"line":1,"column":1}},"key":"Wha3Bpie4p"}],"identifier":"overview","label":"Overview","html_id":"overview","implicit":true,"key":"sOkLxaSH8h"},{"type":"paragraph","position":{"start":{"line":2,"column":1},"end":{"line":2,"column":1}},"children":[{"type":"text","value":"This notebook will cover all the steps to access bright meteor and fireball impact data collected by NASA’s CNEOS and produce a global plot of impact sites","position":{"start":{"line":2,"column":1},"end":{"line":2,"column":1}},"key":"WVhmKzFRgr"}],"key":"wQN1619dmz"},{"type":"list","ordered":true,"start":1,"spread":false,"position":{"start":{"line":4,"column":1},"end":{"line":9,"column":1}},"children":[{"type":"listItem","spread":true,"position":{"start":{"line":4,"column":1},"end":{"line":4,"column":1}},"children":[{"type":"text","value":"Prerequisites","position":{"start":{"line":4,"column":1},"end":{"line":4,"column":1}},"key":"eE9LWnAKKw"}],"key":"TEHfbxHhzZ"},{"type":"listItem","spread":true,"position":{"start":{"line":5,"column":1},"end":{"line":5,"column":1}},"children":[{"type":"text","value":"CNEOS Overview","position":{"start":{"line":5,"column":1},"end":{"line":5,"column":1}},"key":"mTGTwCR5s2"}],"key":"yUCiT5i5PZ"},{"type":"listItem","spread":true,"position":{"start":{"line":6,"column":1},"end":{"line":6,"column":1}},"children":[{"type":"text","value":"Imports","position":{"start":{"line":6,"column":1},"end":{"line":6,"column":1}},"key":"W89vWbjHVu"}],"key":"djlbe9dSsN"},{"type":"listItem","spread":true,"position":{"start":{"line":7,"column":1},"end":{"line":7,"column":1}},"children":[{"type":"text","value":"Access and Organize Data","position":{"start":{"line":7,"column":1},"end":{"line":7,"column":1}},"key":"q4OCbPy2MI"}],"key":"hH2ZkouhsC"},{"type":"listItem","spread":true,"position":{"start":{"line":8,"column":1},"end":{"line":8,"column":1}},"children":[{"type":"text","value":"Plot Earth Fireball Impacts","position":{"start":{"line":8,"column":1},"end":{"line":8,"column":1}},"key":"E5kckmnPFa"}],"key":"w00A2afNJO"},{"type":"listItem","spread":true,"position":{"start":{"line":9,"column":1},"end":{"line":9,"column":1}},"children":[{"type":"text","value":"Summary","position":{"start":{"line":9,"column":1},"end":{"line":9,"column":1}},"key":"eNNN5f9af0"}],"key":"YDCA8uiLXj"}],"key":"JRMXgANtr5"}],"key":"lHGgNwWzgH"},{"type":"block","kind":"notebook-content","children":[{"type":"heading","depth":2,"position":{"start":{"line":1,"column":1},"end":{"line":1,"column":1}},"children":[{"type":"text","value":"Prerequisites","position":{"start":{"line":1,"column":1},"end":{"line":1,"column":1}},"key":"aCfY0DiN6u"}],"identifier":"prerequisites","label":"Prerequisites","html_id":"prerequisites","implicit":true,"key":"FrM3ya69eh"},{"type":"table","position":{"start":{"line":2,"column":1},"end":{"line":6,"column":1}},"children":[{"type":"tableRow","position":{"start":{"line":2,"column":1},"end":{"line":2,"column":1}},"children":[{"type":"tableCell","header":true,"position":{"start":{"line":2,"column":1},"end":{"line":2,"column":1}},"children":[{"type":"text","value":"Concepts","position":{"start":{"line":2,"column":1},"end":{"line":2,"column":1}},"key":"iBeLCjjXE3"}],"key":"RtIJTk7bZ0"},{"type":"tableCell","header":true,"position":{"start":{"line":2,"column":1},"end":{"line":2,"column":1}},"children":[{"type":"text","value":"Importance","position":{"start":{"line":2,"column":1},"end":{"line":2,"column":1}},"key":"BEGHmcc18j"}],"key":"NRz4zbq2s8"},{"type":"tableCell","header":true,"position":{"start":{"line":2,"column":1},"end":{"line":2,"column":1}},"children":[{"type":"text","value":"Notes","position":{"start":{"line":2,"column":1},"end":{"line":2,"column":1}},"key":"Qjjd18g8sl"}],"key":"BKMKedkxSX"}],"key":"yVgnWaEkxN"},{"type":"tableRow","position":{"start":{"line":4,"column":1},"end":{"line":4,"column":1}},"children":[{"type":"tableCell","position":{"start":{"line":4,"column":1},"end":{"line":4,"column":1}},"children":[{"type":"link","url":"https://foundations.projectpythia.org/core/matplotlib/matplotlib-basics.html","position":{"start":{"line":4,"column":1},"end":{"line":4,"column":1}},"children":[{"type":"text","value":"Intro to Matplotlib","position":{"start":{"line":4,"column":1},"end":{"line":4,"column":1}},"key":"P3CyhukgTS"}],"urlSource":"https://foundations.projectpythia.org/core/matplotlib/matplotlib-basics.html","key":"Qy2c7AvU8c"}],"key":"zwnOMyddvb"},{"type":"tableCell","position":{"start":{"line":4,"column":1},"end":{"line":4,"column":1}},"children":[{"type":"text","value":"Necessary","position":{"start":{"line":4,"column":1},"end":{"line":4,"column":1}},"key":"RRY4h0xwrp"}],"key":"J8IGOcbUkc"},{"type":"tableCell","position":{"start":{"line":4,"column":1},"end":{"line":4,"column":1}},"children":[{"type":"text","value":"Plotting on a data","position":{"start":{"line":4,"column":1},"end":{"line":4,"column":1}},"key":"whOpMO6UVX"}],"key":"u1NeSqwKQk"}],"key":"QPa12TOmRE"},{"type":"tableRow","position":{"start":{"line":5,"column":1},"end":{"line":5,"column":1}},"children":[{"type":"tableCell","position":{"start":{"line":5,"column":1},"end":{"line":5,"column":1}},"children":[{"type":"link","url":"https://geopandas.org/en/stable/","position":{"start":{"line":5,"column":1},"end":{"line":5,"column":1}},"children":[{"type":"text","value":"Intro to GeoPandas","position":{"start":{"line":5,"column":1},"end":{"line":5,"column":1}},"key":"PXKeeMBT0h"}],"urlSource":"https://geopandas.org/en/stable/","key":"oS7QULpO2b"}],"key":"Gag7NRdjtm"},{"type":"tableCell","position":{"start":{"line":5,"column":1},"end":{"line":5,"column":1}},"children":[{"type":"text","value":"Necessary","position":{"start":{"line":5,"column":1},"end":{"line":5,"column":1}},"key":"naJkzetF1R"}],"key":"NR18wooU5r"},{"type":"tableCell","position":{"start":{"line":5,"column":1},"end":{"line":5,"column":1}},"children":[{"type":"text","value":"Plotting on a world map","position":{"start":{"line":5,"column":1},"end":{"line":5,"column":1}},"key":"eVjwA6IiTY"}],"key":"rUbLjWBiY2"}],"key":"Fh7O6NFRg7"},{"type":"tableRow","position":{"start":{"line":6,"column":1},"end":{"line":6,"column":1}},"children":[{"type":"tableCell","position":{"start":{"line":6,"column":1},"end":{"line":6,"column":1}},"children":[{"type":"link","url":"https://foundations.projectpythia.org/core/pandas/pandas.html","position":{"start":{"line":6,"column":1},"end":{"line":6,"column":1}},"children":[{"type":"text","value":"Intro to Pandas","position":{"start":{"line":6,"column":1},"end":{"line":6,"column":1}},"key":"oAXb19wT1X"}],"urlSource":"https://foundations.projectpythia.org/core/pandas/pandas.html","key":"Ue3Zwn3ZoY"}],"key":"tiKgUCqbdE"},{"type":"tableCell","position":{"start":{"line":6,"column":1},"end":{"line":6,"column":1}},"children":[{"type":"text","value":"Necessary","position":{"start":{"line":6,"column":1},"end":{"line":6,"column":1}},"key":"nvqhZAPJE3"}],"key":"if1FwwXDKB"},{"type":"tableCell","position":{"start":{"line":6,"column":1},"end":{"line":6,"column":1}},"children":[{"type":"text","value":"Familiarity with working with dataframes","position":{"start":{"line":6,"column":1},"end":{"line":6,"column":1}},"key":"rBZZnwf6zJ"}],"key":"qgYF4J5wMy"}],"key":"XkL8Jnl4ED"}],"key":"s1KMxBovij"}],"key":"I9QGp6k7vg"},{"type":"block","kind":"notebook-content","children":[{"type":"thematicBreak","position":{"start":{"line":1,"column":1},"end":{"line":1,"column":1}},"key":"HoVrE4bSxk"}],"key":"dAkPIwMQeP"},{"type":"block","kind":"notebook-content","children":[{"type":"heading","depth":2,"position":{"start":{"line":1,"column":1},"end":{"line":1,"column":1}},"children":[{"type":"text","value":"CNEOS Overivew","position":{"start":{"line":1,"column":1},"end":{"line":1,"column":1}},"key":"w6Y30jZ6Ji"}],"identifier":"cneos-overivew","label":"CNEOS Overivew","html_id":"cneos-overivew","implicit":true,"key":"cO8p0HG0zh"}],"key":"BoeVNy97ge"},{"type":"block","kind":"notebook-content","children":[{"type":"paragraph","position":{"start":{"line":1,"column":1},"end":{"line":1,"column":1}},"children":[{"type":"text","value":"A shooting star is a common term for a meteor and form bright trails of light that are often bright enough to be visible during the day. A “fireball” is a term for expectionally bright meteor that enters the Earth’s atmosphere at high speeds. A meteor that form fireballs can be over one meter long. A “bolide” typically refers to a fireball that breaks up in the atmosphere. These objects are tracked by the ","position":{"start":{"line":1,"column":1},"end":{"line":1,"column":1}},"key":"Fs14dt9CmA"},{"type":"link","url":"https://cneos.jpl.nasa.gov/","position":{"start":{"line":1,"column":1},"end":{"line":1,"column":1}},"children":[{"type":"text","value":"Center for Near Earth Object Studies (CNEOS)","position":{"start":{"line":1,"column":1},"end":{"line":1,"column":1}},"key":"XFaPwcOGsR"}],"urlSource":"https://cneos.jpl.nasa.gov/","key":"jAIcdgqCix"},{"type":"text","value":" and information about the Peak Brightness, Velocity, and Joules of energy radiatated can be retrieved from CNEOS via an API","position":{"start":{"line":1,"column":1},"end":{"line":1,"column":1}},"key":"joVSilGInJ"}],"key":"lDvfsXdVxg"}],"key":"p5cM5cllxi"},{"type":"block","kind":"notebook-content","children":[{"type":"heading","depth":3,"position":{"start":{"line":1,"column":1},"end":{"line":1,"column":1}},"children":[{"type":"text","value":"Fireball Data API","position":{"start":{"line":1,"column":1},"end":{"line":1,"column":1}},"key":"ulXF7Ar26z"}],"identifier":"fireball-data-api","label":"Fireball Data API","html_id":"fireball-data-api","implicit":true,"key":"XWyooDYK2b"}],"key":"iBBxMhs7Wn"},{"type":"block","kind":"notebook-content","children":[{"type":"paragraph","position":{"start":{"line":1,"column":1},"end":{"line":1,"column":1}},"children":[{"type":"text","value":"This notebook will query the Fireball API for data from the last decade of observations","position":{"start":{"line":1,"column":1},"end":{"line":1,"column":1}},"key":"ZuGisdtuCH"}],"key":"jWKGTKDptt"},{"type":"paragraph","position":{"start":{"line":3,"column":1},"end":{"line":3,"column":1}},"children":[{"type":"text","value":"JPL’s Center for Near-Earth Objects Studies ","position":{"start":{"line":3,"column":1},"end":{"line":3,"column":1}},"key":"lt4aKr5ukv"},{"type":"link","url":"https://ssd-api.jpl.nasa.gov/doc/fireball.html","position":{"start":{"line":3,"column":1},"end":{"line":3,"column":1}},"children":[{"type":"text","value":"API “Fireball”","position":{"start":{"line":3,"column":1},"end":{"line":3,"column":1}},"key":"ZVSkUZcRNl"}],"urlSource":"https://ssd-api.jpl.nasa.gov/doc/fireball.html","key":"BpoUgjusj6"},{"type":"text","value":" is an API that will return machine-readable data in the form of a JSON.","position":{"start":{"line":3,"column":1},"end":{"line":3,"column":1}},"key":"f9wYzicGD8"}],"key":"gUAoB5hXEa"},{"type":"paragraph","position":{"start":{"line":5,"column":1},"end":{"line":5,"column":1}},"children":[{"type":"text","value":"All queries to the Fireball Data API make requests to ","position":{"start":{"line":5,"column":1},"end":{"line":5,"column":1}},"key":"jb3KwhmmFz"},{"type":"inlineCode","value":"https://ssd-api.jpl.nasa.gov/fireball.api","position":{"start":{"line":5,"column":1},"end":{"line":5,"column":1}},"key":"Zy9q0pqVLR"}],"key":"bhRfvMhWLz"},{"type":"paragraph","position":{"start":{"line":7,"column":1},"end":{"line":7,"column":1}},"children":[{"type":"text","value":"The API accepts different query parameters to filter the data","position":{"start":{"line":7,"column":1},"end":{"line":7,"column":1}},"key":"KkbnlYHwcH"}],"key":"EwiyfhXRZ7"},{"type":"paragraph","position":{"start":{"line":9,"column":1},"end":{"line":9,"column":1}},"children":[{"type":"text","value":"Directly querying ","position":{"start":{"line":9,"column":1},"end":{"line":9,"column":1}},"key":"YYaGRC6KNs"},{"type":"inlineCode","value":"https://ssd-api.jpl.nasa.gov/fireball.api","position":{"start":{"line":9,"column":1},"end":{"line":9,"column":1}},"key":"rQ1rLMqYP0"},{"type":"text","value":" will return all the data of fireball impacts in reverse-chronological order","position":{"start":{"line":9,"column":1},"end":{"line":9,"column":1}},"key":"joTUgfzW8O"}],"key":"EsZiaowgmZ"},{"type":"table","position":{"start":{"line":11,"column":1},"end":{"line":26,"column":1}},"children":[{"type":"tableRow","position":{"start":{"line":11,"column":1},"end":{"line":11,"column":1}},"children":[{"type":"tableCell","header":true,"position":{"start":{"line":11,"column":1},"end":{"line":11,"column":1}},"children":[{"type":"text","value":"Parameter","position":{"start":{"line":11,"column":1},"end":{"line":11,"column":1}},"key":"OlQiSRC7G5"}],"key":"qZTyOl2NNL"},{"type":"tableCell","header":true,"position":{"start":{"line":11,"column":1},"end":{"line":11,"column":1}},"children":[{"type":"text","value":"Type","position":{"start":{"line":11,"column":1},"end":{"line":11,"column":1}},"key":"Ypu66If0ef"}],"key":"CDJnycXsbH"},{"type":"tableCell","header":true,"position":{"start":{"line":11,"column":1},"end":{"line":11,"column":1}},"children":[{"type":"text","value":"Description","position":{"start":{"line":11,"column":1},"end":{"line":11,"column":1}},"key":"DDVZ0E3QkL"}],"key":"yr6eeIPG9D"}],"key":"OqUTVUurZ6"},{"type":"tableRow","position":{"start":{"line":13,"column":1},"end":{"line":13,"column":1}},"children":[{"type":"tableCell","position":{"start":{"line":13,"column":1},"end":{"line":13,"column":1}},"children":[{"type":"text","value":"date-min","position":{"start":{"line":13,"column":1},"end":{"line":13,"column":1}},"key":"zO3YKkFgaJ"}],"key":"Hy6ov8xHH0"},{"type":"tableCell","position":{"start":{"line":13,"column":1},"end":{"line":13,"column":1}},"children":[{"type":"text","value":"string","position":{"start":{"line":13,"column":1},"end":{"line":13,"column":1}},"key":"oy0ebpUGVS"}],"key":"cEmaEKSWbK"},{"type":"tableCell","position":{"start":{"line":13,"column":1},"end":{"line":13,"column":1}},"children":[{"type":"text","value":"exclude data earlier than this date ","position":{"start":{"line":13,"column":1},"end":{"line":13,"column":1}},"key":"U1FgXyqNHW"},{"type":"inlineCode","value":"YYYY-MM-DD","position":{"start":{"line":13,"column":1},"end":{"line":13,"column":1}},"key":"uRrhNhB5pl"},{"type":"text","value":" or date/time ","position":{"start":{"line":13,"column":1},"end":{"line":13,"column":1}},"key":"mySZSWhFco"},{"type":"inlineCode","value":"YYYY-MM-DDThh:mm:ss","position":{"start":{"line":13,"column":1},"end":{"line":13,"column":1}},"key":"mK4gdSf0yW"}],"key":"Xhew55LsTl"}],"key":"Y0g0aWDnBg"},{"type":"tableRow","position":{"start":{"line":14,"column":1},"end":{"line":14,"column":1}},"children":[{"type":"tableCell","position":{"start":{"line":14,"column":1},"end":{"line":14,"column":1}},"children":[{"type":"text","value":"date-max","position":{"start":{"line":14,"column":1},"end":{"line":14,"column":1}},"key":"uQTivPMEXA"}],"key":"OwJXyB6ZbQ"},{"type":"tableCell","position":{"start":{"line":14,"column":1},"end":{"line":14,"column":1}},"children":[{"type":"text","value":"string","position":{"start":{"line":14,"column":1},"end":{"line":14,"column":1}},"key":"iPwUIoHDgS"}],"key":"QOtWqgD7Rx"},{"type":"tableCell","position":{"start":{"line":14,"column":1},"end":{"line":14,"column":1}},"children":[{"type":"text","value":"exclude data later than this date ","position":{"start":{"line":14,"column":1},"end":{"line":14,"column":1}},"key":"h24ll1Kty2"},{"type":"inlineCode","value":"YYYY-MM-DD","position":{"start":{"line":14,"column":1},"end":{"line":14,"column":1}},"key":"KK4MqEELO2"},{"type":"text","value":" or date/time ","position":{"start":{"line":14,"column":1},"end":{"line":14,"column":1}},"key":"rIfPEBVrD7"},{"type":"inlineCode","value":"YYYY-MM-DDThh:mm:ss","position":{"start":{"line":14,"column":1},"end":{"line":14,"column":1}},"key":"csSropz8d1"}],"key":"XQsswnniEA"}],"key":"rp3flZt8yH"},{"type":"tableRow","position":{"start":{"line":15,"column":1},"end":{"line":15,"column":1}},"children":[{"type":"tableCell","position":{"start":{"line":15,"column":1},"end":{"line":15,"column":1}},"children":[{"type":"text","value":"energy-min","position":{"start":{"line":15,"column":1},"end":{"line":15,"column":1}},"key":"n23XoEJXfH"}],"key":"oBxWof21KY"},{"type":"tableCell","position":{"start":{"line":15,"column":1},"end":{"line":15,"column":1}},"children":[{"type":"text","value":"string","position":{"start":{"line":15,"column":1},"end":{"line":15,"column":1}},"key":"vemQrxuk63"}],"key":"cFcRCN3jYB"},{"type":"tableCell","position":{"start":{"line":15,"column":1},"end":{"line":15,"column":1}},"children":[{"type":"text","value":"exclude data with total-radiated-energy less than this positive value in joules ×1010 (e.g., ","position":{"start":{"line":15,"column":1},"end":{"line":15,"column":1}},"key":"XvPFMsHpN6"},{"type":"inlineCode","value":"0.3","position":{"start":{"line":15,"column":1},"end":{"line":15,"column":1}},"key":"WrB6kmGTDo"},{"type":"text","value":" = 0.3×1010 joules)","position":{"start":{"line":15,"column":1},"end":{"line":15,"column":1}},"key":"IZNCPj5IMp"}],"key":"Nf6j3rHFmW"}],"key":"KlmgbnLo0W"},{"type":"tableRow","position":{"start":{"line":16,"column":1},"end":{"line":16,"column":1}},"children":[{"type":"tableCell","position":{"start":{"line":16,"column":1},"end":{"line":16,"column":1}},"children":[{"type":"text","value":"energy-max","position":{"start":{"line":16,"column":1},"end":{"line":16,"column":1}},"key":"mWX8hQNUd0"}],"key":"k5DUmiyzSZ"},{"type":"tableCell","position":{"start":{"line":16,"column":1},"end":{"line":16,"column":1}},"children":[{"type":"text","value":"string","position":{"start":{"line":16,"column":1},"end":{"line":16,"column":1}},"key":"kvrpFrvq8M"}],"key":"wni51YEm5n"},{"type":"tableCell","position":{"start":{"line":16,"column":1},"end":{"line":16,"column":1}},"children":[{"type":"text","value":"exclude data with total-radiated-energy greater than this (see energy-min)","position":{"start":{"line":16,"column":1},"end":{"line":16,"column":1}},"key":"ozzR0R8Ry7"}],"key":"ZiLhsI7hB8"}],"key":"KAB2wevtDM"},{"type":"tableRow","position":{"start":{"line":17,"column":1},"end":{"line":17,"column":1}},"children":[{"type":"tableCell","position":{"start":{"line":17,"column":1},"end":{"line":17,"column":1}},"children":[{"type":"text","value":"impact-e-min","position":{"start":{"line":17,"column":1},"end":{"line":17,"column":1}},"key":"T1KUtUAlRY"}],"key":"jRV1Sws1Bc"},{"type":"tableCell","position":{"start":{"line":17,"column":1},"end":{"line":17,"column":1}},"children":[{"type":"text","value":"string","position":{"start":{"line":17,"column":1},"end":{"line":17,"column":1}},"key":"loMhC2zGDc"}],"key":"nKl26TANVV"},{"type":"tableCell","position":{"start":{"line":17,"column":1},"end":{"line":17,"column":1}},"children":[{"type":"text","value":"exclude data with estimated impact energy less than this positive value in kilotons (kt) (e.g., ","position":{"start":{"line":17,"column":1},"end":{"line":17,"column":1}},"key":"n39omMbws6"},{"type":"inlineCode","value":"0.08","position":{"start":{"line":17,"column":1},"end":{"line":17,"column":1}},"key":"kc2tc9K3Ir"},{"type":"text","value":" kt)","position":{"start":{"line":17,"column":1},"end":{"line":17,"column":1}},"key":"tQPYzbhEjV"}],"key":"CTSLfdpA5H"}],"key":"EsZCsciKao"},{"type":"tableRow","position":{"start":{"line":18,"column":1},"end":{"line":18,"column":1}},"children":[{"type":"tableCell","position":{"start":{"line":18,"column":1},"end":{"line":18,"column":1}},"children":[{"type":"text","value":"impact-e-max","position":{"start":{"line":18,"column":1},"end":{"line":18,"column":1}},"key":"owpZDPRbE7"}],"key":"XCYh4LYW51"},{"type":"tableCell","position":{"start":{"line":18,"column":1},"end":{"line":18,"column":1}},"children":[{"type":"text","value":"string","position":{"start":{"line":18,"column":1},"end":{"line":18,"column":1}},"key":"fuilnyzHMQ"}],"key":"I8SfJPLB16"},{"type":"tableCell","position":{"start":{"line":18,"column":1},"end":{"line":18,"column":1}},"children":[{"type":"text","value":"exclude data with total-radiated-energy greater than this (see impact-e-min)","position":{"start":{"line":18,"column":1},"end":{"line":18,"column":1}},"key":"McHy3CgOcd"}],"key":"Gj0dEOUakN"}],"key":"rlD3FFWMTz"},{"type":"tableRow","position":{"start":{"line":19,"column":1},"end":{"line":19,"column":1}},"children":[{"type":"tableCell","position":{"start":{"line":19,"column":1},"end":{"line":19,"column":1}},"children":[{"type":"text","value":"alt-min","position":{"start":{"line":19,"column":1},"end":{"line":19,"column":1}},"key":"iApEBQ2pTt"}],"key":"YTYZQDBu1p"},{"type":"tableCell","position":{"start":{"line":19,"column":1},"end":{"line":19,"column":1}},"children":[{"type":"text","value":"number","position":{"start":{"line":19,"column":1},"end":{"line":19,"column":1}},"key":"HuWPWkh1Fp"}],"key":"BGNLUnjL3Z"},{"type":"tableCell","position":{"start":{"line":19,"column":1},"end":{"line":19,"column":1}},"children":[{"type":"text","value":"exclude data from objects with an altitude less than this (e.g., ","position":{"start":{"line":19,"column":1},"end":{"line":19,"column":1}},"key":"Fb8WoMcoBi"},{"type":"inlineCode","value":"22","position":{"start":{"line":19,"column":1},"end":{"line":19,"column":1}},"key":"Waz1UkyVi8"},{"type":"text","value":" meaning objects smaller than this)","position":{"start":{"line":19,"column":1},"end":{"line":19,"column":1}},"key":"JYBz4FgNy2"}],"key":"d2AusQKbOK"}],"key":"mOdqFgBJde"},{"type":"tableRow","position":{"start":{"line":20,"column":1},"end":{"line":20,"column":1}},"children":[{"type":"tableCell","position":{"start":{"line":20,"column":1},"end":{"line":20,"column":1}},"children":[{"type":"text","value":"alt-max","position":{"start":{"line":20,"column":1},"end":{"line":20,"column":1}},"key":"HC3ecXfJKo"}],"key":"GSjoMSA4iS"},{"type":"tableCell","position":{"start":{"line":20,"column":1},"end":{"line":20,"column":1}},"children":[{"type":"text","value":"number","position":{"start":{"line":20,"column":1},"end":{"line":20,"column":1}},"key":"YlCIaQLOTb"}],"key":"X2eU1qWMlO"},{"type":"tableCell","position":{"start":{"line":20,"column":1},"end":{"line":20,"column":1}},"children":[{"type":"text","value":"exclude data from objects with an altitude greater than this (e.g., ","position":{"start":{"line":20,"column":1},"end":{"line":20,"column":1}},"key":"GoQTEAtZkx"},{"type":"inlineCode","value":"17.75","position":{"start":{"line":20,"column":1},"end":{"line":20,"column":1}},"key":"QBpVD3xTTt"},{"type":"text","value":" meaning objects larger than this)","position":{"start":{"line":20,"column":1},"end":{"line":20,"column":1}},"key":"pcR2ESNDIS"}],"key":"h9zF8WwyNd"}],"key":"zbMli7ka1n"},{"type":"tableRow","position":{"start":{"line":21,"column":1},"end":{"line":21,"column":1}},"children":[{"type":"tableCell","position":{"start":{"line":21,"column":1},"end":{"line":21,"column":1}},"children":[{"type":"text","value":"req-loc","position":{"start":{"line":21,"column":1},"end":{"line":21,"column":1}},"key":"DlK7NbNTwm"}],"key":"JYyD7Fn8Zv"},{"type":"tableCell","position":{"start":{"line":21,"column":1},"end":{"line":21,"column":1}},"children":[{"type":"text","value":"boolean","position":{"start":{"line":21,"column":1},"end":{"line":21,"column":1}},"key":"x7VGryRlvW"}],"key":"L30LUw7obW"},{"type":"tableCell","position":{"start":{"line":21,"column":1},"end":{"line":21,"column":1}},"children":[{"type":"text","value":"location (latitude and longitude) required; when set ","position":{"start":{"line":21,"column":1},"end":{"line":21,"column":1}},"key":"KMNniAIYFC"},{"type":"inlineCode","value":"true","position":{"start":{"line":21,"column":1},"end":{"line":21,"column":1}},"key":"TAJWzOIpqB"},{"type":"text","value":", exclude data without a location","position":{"start":{"line":21,"column":1},"end":{"line":21,"column":1}},"key":"kFdnj38sT2"}],"key":"S5saQbpBCw"}],"key":"kZYJq6N55e"},{"type":"tableRow","position":{"start":{"line":22,"column":1},"end":{"line":22,"column":1}},"children":[{"type":"tableCell","position":{"start":{"line":22,"column":1},"end":{"line":22,"column":1}},"children":[{"type":"text","value":"req-alt","position":{"start":{"line":22,"column":1},"end":{"line":22,"column":1}},"key":"STZN6qJwZd"}],"key":"FzmMCqyjPS"},{"type":"tableCell","position":{"start":{"line":22,"column":1},"end":{"line":22,"column":1}},"children":[{"type":"text","value":"boolean","position":{"start":{"line":22,"column":1},"end":{"line":22,"column":1}},"key":"w5QFPsELLF"}],"key":"hQUv0L2uqf"},{"type":"tableCell","position":{"start":{"line":22,"column":1},"end":{"line":22,"column":1}},"children":[{"type":"text","value":"altitude required; when set ","position":{"start":{"line":22,"column":1},"end":{"line":22,"column":1}},"key":"yiBSvh1Gbq"},{"type":"inlineCode","value":"true","position":{"start":{"line":22,"column":1},"end":{"line":22,"column":1}},"key":"tmONkFTI8k"},{"type":"text","value":", exclude data without an altitude","position":{"start":{"line":22,"column":1},"end":{"line":22,"column":1}},"key":"uxtl6nPJTc"}],"key":"KtVOzDBrHb"}],"key":"lkylc1q3lg"},{"type":"tableRow","position":{"start":{"line":23,"column":1},"end":{"line":23,"column":1}},"children":[{"type":"tableCell","position":{"start":{"line":23,"column":1},"end":{"line":23,"column":1}},"children":[{"type":"text","value":"req-vel-comp","position":{"start":{"line":23,"column":1},"end":{"line":23,"column":1}},"key":"jAf3sVRQeM"}],"key":"fqUgYA5uc8"},{"type":"tableCell","position":{"start":{"line":23,"column":1},"end":{"line":23,"column":1}},"children":[{"type":"text","value":"boolean","position":{"start":{"line":23,"column":1},"end":{"line":23,"column":1}},"key":"H2NntxHpif"}],"key":"Ts05RfxJ1H"},{"type":"tableCell","position":{"start":{"line":23,"column":1},"end":{"line":23,"column":1}},"children":[{"type":"text","value":"pre-entry velocity components required; when set ","position":{"start":{"line":23,"column":1},"end":{"line":23,"column":1}},"key":"gTmhzjlMak"},{"type":"inlineCode","value":"true","position":{"start":{"line":23,"column":1},"end":{"line":23,"column":1}},"key":"YYOm2UnUu5"},{"type":"text","value":", exclude data without pre-entry velocity components","position":{"start":{"line":23,"column":1},"end":{"line":23,"column":1}},"key":"eP7EeFDXBF"}],"key":"DRKJhZPQD3"}],"key":"zJFRm8s32V"},{"type":"tableRow","position":{"start":{"line":24,"column":1},"end":{"line":24,"column":1}},"children":[{"type":"tableCell","position":{"start":{"line":24,"column":1},"end":{"line":24,"column":1}},"children":[{"type":"text","value":"vel-comp","position":{"start":{"line":24,"column":1},"end":{"line":24,"column":1}},"key":"mQ785wJR3c"}],"key":"ipXaTszSjV"},{"type":"tableCell","position":{"start":{"line":24,"column":1},"end":{"line":24,"column":1}},"children":[{"type":"text","value":"boolean","position":{"start":{"line":24,"column":1},"end":{"line":24,"column":1}},"key":"AvoO0piZ2o"}],"key":"dbNES0a81U"},{"type":"tableCell","position":{"start":{"line":24,"column":1},"end":{"line":24,"column":1}},"children":[{"type":"text","value":"include pre-entry velocity components","position":{"start":{"line":24,"column":1},"end":{"line":24,"column":1}},"key":"kstsP9oNUC"}],"key":"Qtz3QdZ97b"}],"key":"ICJxkM0TJT"},{"type":"tableRow","position":{"start":{"line":25,"column":1},"end":{"line":25,"column":1}},"children":[{"type":"tableCell","position":{"start":{"line":25,"column":1},"end":{"line":25,"column":1}},"children":[{"type":"text","value":"sort","position":{"start":{"line":25,"column":1},"end":{"line":25,"column":1}},"key":"kpm1lAeTGF"}],"key":"iu7O5Zmkzr"},{"type":"tableCell","position":{"start":{"line":25,"column":1},"end":{"line":25,"column":1}},"children":[{"type":"text","value":"string","position":{"start":{"line":25,"column":1},"end":{"line":25,"column":1}},"key":"ajWD2yC28r"}],"key":"D6b9kmUMv5"},{"type":"tableCell","position":{"start":{"line":25,"column":1},"end":{"line":25,"column":1}},"children":[{"type":"text","value":"sort data on the specified field: “date”, “energy”, “impact-e”, “vel”, or “alt” (default sort order is ascending: prepend “-“ for descending)","position":{"start":{"line":25,"column":1},"end":{"line":25,"column":1}},"key":"R1e9shpvAr"}],"key":"iFjqvt770g"}],"key":"EacSTY9Wep"},{"type":"tableRow","position":{"start":{"line":26,"column":1},"end":{"line":26,"column":1}},"children":[{"type":"tableCell","position":{"start":{"line":26,"column":1},"end":{"line":26,"column":1}},"children":[{"type":"text","value":"limit","position":{"start":{"line":26,"column":1},"end":{"line":26,"column":1}},"key":"nTadYQ1qiX"}],"key":"oAa4Ongru9"},{"type":"tableCell","position":{"start":{"line":26,"column":1},"end":{"line":26,"column":1}},"children":[{"type":"text","value":"number","position":{"start":{"line":26,"column":1},"end":{"line":26,"column":1}},"key":"AgzuymnK2F"}],"key":"O5mls3VUIs"},{"type":"tableCell","position":{"start":{"line":26,"column":1},"end":{"line":26,"column":1}},"children":[{"type":"text","value":"limit data to the first N results (where N is the specified number and must be an integer value greater than zero)","position":{"start":{"line":26,"column":1},"end":{"line":26,"column":1}},"key":"Cjtzi0SqLd"}],"key":"bMox2BtQMx"}],"key":"ss8B2PvALc"}],"key":"Td2KGrcM4Z"},{"type":"paragraph","position":{"start":{"line":28,"column":1},"end":{"line":28,"column":1}},"children":[{"type":"text","value":"Results from API will be returned as JSON with a number of fields","position":{"start":{"line":28,"column":1},"end":{"line":28,"column":1}},"key":"pJ2Fl7eDrU"}],"key":"yyA67yHVeU"},{"type":"table","position":{"start":{"line":30,"column":1},"end":{"line":42,"column":1}},"children":[{"type":"tableRow","position":{"start":{"line":30,"column":1},"end":{"line":30,"column":1}},"children":[{"type":"tableCell","header":true,"position":{"start":{"line":30,"column":1},"end":{"line":30,"column":1}},"children":[{"type":"text","value":"Field","position":{"start":{"line":30,"column":1},"end":{"line":30,"column":1}},"key":"BswZxbeLJs"}],"key":"lE9UshHZ0B"},{"type":"tableCell","header":true,"position":{"start":{"line":30,"column":1},"end":{"line":30,"column":1}},"children":[{"type":"text","value":"Description","position":{"start":{"line":30,"column":1},"end":{"line":30,"column":1}},"key":"cjm1DjH8xM"}],"key":"a1etP2eEkW"}],"key":"nWdn6jwS2u"},{"type":"tableRow","position":{"start":{"line":32,"column":1},"end":{"line":32,"column":1}},"children":[{"type":"tableCell","position":{"start":{"line":32,"column":1},"end":{"line":32,"column":1}},"children":[{"type":"text","value":"date","position":{"start":{"line":32,"column":1},"end":{"line":32,"column":1}},"key":"DlmGUtpAVP"}],"key":"Cy1l723ak3"},{"type":"tableCell","position":{"start":{"line":32,"column":1},"end":{"line":32,"column":1}},"children":[{"type":"text","value":"date/time of peak brightness (GMT)","position":{"start":{"line":32,"column":1},"end":{"line":32,"column":1}},"key":"vFjUsKEFfn"}],"key":"xKj1lniFp6"}],"key":"Zm1DZS0KWk"},{"type":"tableRow","position":{"start":{"line":33,"column":1},"end":{"line":33,"column":1}},"children":[{"type":"tableCell","position":{"start":{"line":33,"column":1},"end":{"line":33,"column":1}},"children":[{"type":"text","value":"lat","position":{"start":{"line":33,"column":1},"end":{"line":33,"column":1}},"key":"BiIfsKMGIe"}],"key":"Wz7TjzGoX8"},{"type":"tableCell","position":{"start":{"line":33,"column":1},"end":{"line":33,"column":1}},"children":[{"type":"text","value":"latitude at peak brightness (degrees)","position":{"start":{"line":33,"column":1},"end":{"line":33,"column":1}},"key":"CjhColxYzY"}],"key":"PoEJIgS20D"}],"key":"o9jDIYkkgs"},{"type":"tableRow","position":{"start":{"line":34,"column":1},"end":{"line":34,"column":1}},"children":[{"type":"tableCell","position":{"start":{"line":34,"column":1},"end":{"line":34,"column":1}},"children":[{"type":"text","value":"lon","position":{"start":{"line":34,"column":1},"end":{"line":34,"column":1}},"key":"djMymuUZZN"}],"key":"wPglu27FTo"},{"type":"tableCell","position":{"start":{"line":34,"column":1},"end":{"line":34,"column":1}},"children":[{"type":"text","value":"longitude at peak brightness (degrees)","position":{"start":{"line":34,"column":1},"end":{"line":34,"column":1}},"key":"nQIQ6z5frq"}],"key":"p1tAAAdkjr"}],"key":"Lxcc3yvBGx"},{"type":"tableRow","position":{"start":{"line":35,"column":1},"end":{"line":35,"column":1}},"children":[{"type":"tableCell","position":{"start":{"line":35,"column":1},"end":{"line":35,"column":1}},"children":[{"type":"text","value":"lat-dir","position":{"start":{"line":35,"column":1},"end":{"line":35,"column":1}},"key":"F32D5QnHRP"}],"key":"M0Pq1Uf3yW"},{"type":"tableCell","position":{"start":{"line":35,"column":1},"end":{"line":35,"column":1}},"children":[{"type":"text","value":"latitude direction (“N” or “S”)","position":{"start":{"line":35,"column":1},"end":{"line":35,"column":1}},"key":"UGjhLbQTOb"}],"key":"u8HboCV2eJ"}],"key":"rYi18Eho9x"},{"type":"tableRow","position":{"start":{"line":36,"column":1},"end":{"line":36,"column":1}},"children":[{"type":"tableCell","position":{"start":{"line":36,"column":1},"end":{"line":36,"column":1}},"children":[{"type":"text","value":"lon-dir","position":{"start":{"line":36,"column":1},"end":{"line":36,"column":1}},"key":"oqkiOwbi6h"}],"key":"CilRBqNVel"},{"type":"tableCell","position":{"start":{"line":36,"column":1},"end":{"line":36,"column":1}},"children":[{"type":"text","value":"latitude direction (“E” or “W”)","position":{"start":{"line":36,"column":1},"end":{"line":36,"column":1}},"key":"QfISnHD7ZL"}],"key":"YQ7ZlQSA15"}],"key":"ZF5MMMCsKK"},{"type":"tableRow","position":{"start":{"line":37,"column":1},"end":{"line":37,"column":1}},"children":[{"type":"tableCell","position":{"start":{"line":37,"column":1},"end":{"line":37,"column":1}},"children":[{"type":"text","value":"alt","position":{"start":{"line":37,"column":1},"end":{"line":37,"column":1}},"key":"Rj9V25Fypn"}],"key":"P7GvxjpceC"},{"type":"tableCell","position":{"start":{"line":37,"column":1},"end":{"line":37,"column":1}},"children":[{"type":"text","value":"altitude above the geoid at peak brightness (km)","position":{"start":{"line":37,"column":1},"end":{"line":37,"column":1}},"key":"ej4aXbL9NS"}],"key":"STQ8fsFrlQ"}],"key":"wjNxEKyXjv"},{"type":"tableRow","position":{"start":{"line":38,"column":1},"end":{"line":38,"column":1}},"children":[{"type":"tableCell","position":{"start":{"line":38,"column":1},"end":{"line":38,"column":1}},"children":[{"type":"text","value":"energy","position":{"start":{"line":38,"column":1},"end":{"line":38,"column":1}},"key":"LgxIWsDAJ4"}],"key":"fKC6Ja9Ve4"},{"type":"tableCell","position":{"start":{"line":38,"column":1},"end":{"line":38,"column":1}},"children":[{"type":"text","value":"approximate total radiated energy (10^10 joules)","position":{"start":{"line":38,"column":1},"end":{"line":38,"column":1}},"key":"iFzQzwD6n3"}],"key":"ypZ6LGl6H7"}],"key":"Xzm33z94d9"},{"type":"tableRow","position":{"start":{"line":39,"column":1},"end":{"line":39,"column":1}},"children":[{"type":"tableCell","position":{"start":{"line":39,"column":1},"end":{"line":39,"column":1}},"children":[{"type":"text","value":"impact-e","position":{"start":{"line":39,"column":1},"end":{"line":39,"column":1}},"key":"orNBSeKiEp"}],"key":"onn8TpD5BL"},{"type":"tableCell","position":{"start":{"line":39,"column":1},"end":{"line":39,"column":1}},"children":[{"type":"text","value":"approximate total impact energy (kt)","position":{"start":{"line":39,"column":1},"end":{"line":39,"column":1}},"key":"ycgZqzL2uq"}],"key":"yL9OvzwovY"}],"key":"Jfm0bIeLak"},{"type":"tableRow","position":{"start":{"line":40,"column":1},"end":{"line":40,"column":1}},"children":[{"type":"tableCell","position":{"start":{"line":40,"column":1},"end":{"line":40,"column":1}},"children":[{"type":"text","value":"vx","position":{"start":{"line":40,"column":1},"end":{"line":40,"column":1}},"key":"ZxCpK1eo9k"}],"key":"sHWoEXuHL3"},{"type":"tableCell","position":{"start":{"line":40,"column":1},"end":{"line":40,"column":1}},"children":[{"type":"text","value":"pre-entry velocity (Earth centered X component, km/s)","position":{"start":{"line":40,"column":1},"end":{"line":40,"column":1}},"key":"eyxkuoEO64"}],"key":"xBiwF2d8Tq"}],"key":"kkZzdTgM8f"},{"type":"tableRow","position":{"start":{"line":41,"column":1},"end":{"line":41,"column":1}},"children":[{"type":"tableCell","position":{"start":{"line":41,"column":1},"end":{"line":41,"column":1}},"children":[{"type":"text","value":"vy","position":{"start":{"line":41,"column":1},"end":{"line":41,"column":1}},"key":"dRwvPDlCJ2"}],"key":"wj5FwWeBWs"},{"type":"tableCell","position":{"start":{"line":41,"column":1},"end":{"line":41,"column":1}},"children":[{"type":"text","value":"pre-entry velocity (Earth centered Y component, km/s)","position":{"start":{"line":41,"column":1},"end":{"line":41,"column":1}},"key":"YyYHAlibX7"}],"key":"UBTDkZCino"}],"key":"oILpfLCmfP"},{"type":"tableRow","position":{"start":{"line":42,"column":1},"end":{"line":42,"column":1}},"children":[{"type":"tableCell","position":{"start":{"line":42,"column":1},"end":{"line":42,"column":1}},"children":[{"type":"text","value":"vz","position":{"start":{"line":42,"column":1},"end":{"line":42,"column":1}},"key":"KJ6HeHKDlV"}],"key":"J5Bcac0cjN"},{"type":"tableCell","position":{"start":{"line":42,"column":1},"end":{"line":42,"column":1}},"children":[{"type":"text","value":"pre-entry velocity (Earth centered Z component, km/s)","position":{"start":{"line":42,"column":1},"end":{"line":42,"column":1}},"key":"bIJcvJ3SEz"}],"key":"RDXX641TUH"}],"key":"S0aBcFeH5w"}],"key":"vcgI5vkOqU"},{"type":"heading","depth":2,"position":{"start":{"line":44,"column":1},"end":{"line":44,"column":1}},"children":[{"type":"text","value":"Example JSON result","position":{"start":{"line":44,"column":1},"end":{"line":44,"column":1}},"key":"xqtIwtak5M"}],"identifier":"example-json-result","label":"Example JSON result","html_id":"example-json-result","implicit":true,"key":"rIpgJME7rJ"},{"type":"paragraph","position":{"start":{"line":46,"column":1},"end":{"line":46,"column":1}},"children":[{"type":"text","value":"Return the last 3 records ","position":{"start":{"line":46,"column":1},"end":{"line":46,"column":1}},"key":"GkYsBtW8mR"},{"type":"inlineCode","value":"https://ssd-api.jpl.nasa.gov/fireball.api?limit=3","position":{"start":{"line":46,"column":1},"end":{"line":46,"column":1}},"key":"UkeWBPcdCP"}],"key":"UhtEkYUpxf"},{"type":"code","lang":"","value":"{\n    \"signature\":\n        {\n            \"version\":\"1.0\",\n            \"source\":\"NASA/JPL Fireball Data API\"\n        },\n    \"count\":\"3\",\n    \"fields\":[\"date\",\"energy\",\"impact-e\",\"lat\",\"lat-dir\",\"lon\",\"lon-dir\",\"alt\",\"vel\"],\n    \"data\":[\n        [\"2024-06-03 01:13:51\",\"2.6\",\"0.092\",\"63.1\",\"S\",\"53.2\",\"W\",\"60.0\",null],\n        [\"2024-06-01 23:24:59\",\"7.9\",\"0.25\",\"1.0\",\"S\",\"15.9\",\"W\",\"26.5\",\"12.6\"],\n        [\"2024-05-27 03:19:36\",\"8.4\",\"0.26\",\"1.7\",\"N\",\"39.4\",\"W\",\"56.0\",\"39.2\"]\n    ]\n}","position":{"start":{"line":48,"column":1},"end":{"line":63,"column":1}},"key":"OboKKNwFsx"}],"key":"DhFF854ZOU"},{"type":"block","kind":"notebook-content","children":[{"type":"heading","depth":2,"position":{"start":{"line":1,"column":1},"end":{"line":1,"column":1}},"children":[{"type":"text","value":"Imports","position":{"start":{"line":1,"column":1},"end":{"line":1,"column":1}},"key":"wPluXEuiIr"}],"identifier":"imports","label":"Imports","html_id":"imports","implicit":true,"key":"Rhl0NlNn2a"}],"key":"GmnLsAjuRj"},{"type":"block","kind":"notebook-code","children":[{"type":"code","lang":"python","executable":true,"value":"import requests                 # submit API request query\nimport pandas as pd             # organizes data retrieved by the API\nimport geopandas                # generate a world map\nimport matplotlib.pyplot as plt # plotting data","key":"JG01rgweqU"},{"type":"output","id":"OuOwKVv-X0RQ8miqZPhYq","data":[],"key":"VCOv5AKcQR"}],"key":"GT9pn42W8H"},{"type":"block","kind":"notebook-content","children":[{"type":"heading","depth":2,"position":{"start":{"line":1,"column":1},"end":{"line":1,"column":1}},"children":[{"type":"text","value":"Request Fireball Data via API","position":{"start":{"line":1,"column":1},"end":{"line":1,"column":1}},"key":"QnyxCNzEwA"}],"identifier":"request-fireball-data-via-api","label":"Request Fireball Data via API","html_id":"request-fireball-data-via-api","implicit":true,"key":"CEYdLJCFmu"}],"key":"p6gWdkJYAx"},{"type":"block","kind":"notebook-content","children":[{"type":"paragraph","position":{"start":{"line":1,"column":1},"end":{"line":1,"column":1}},"children":[{"type":"text","value":"To retrieve all the fireballs recorded in the last decade (2014-2024)","position":{"start":{"line":1,"column":1},"end":{"line":1,"column":1}},"key":"Lsyino58jj"}],"key":"guJQYNT1pu"}],"key":"C7aeCpjGqc"},{"type":"block","kind":"notebook-code","children":[{"type":"code","lang":"python","executable":true,"value":"data_since = \"2014-01-01\"\nlast_decade_fireball = requests.get(f\"https://ssd-api.jpl.nasa.gov/fireball.api?date-min={data_since}\")\nlast_decade_fireball.status_code # 200 is a valid request","key":"jh9jZtbLPb"},{"type":"output","id":"-tBZqQrokX1svLPlcFCZs","data":[{"output_type":"execute_result","execution_count":2,"metadata":{},"data":{"text/plain":{"content":"200","content_type":"text/plain"}}}],"key":"EuN6ltR1Mn"}],"key":"ggjJDgkQNJ"},{"type":"block","kind":"notebook-code","children":[{"type":"code","lang":"python","executable":true,"value":"fireball_json = last_decade_fireball.json()","key":"gvpTA0LKUS"},{"type":"output","id":"bHRGeZ7ZrUfiptWLHJE1s","data":[],"key":"SVxWbpnOdT"}],"key":"HW7dAvOJmk"},{"type":"block","kind":"notebook-code","children":[{"type":"code","lang":"python","executable":true,"value":"# print out data labels\nprint(f\"fields = {fireball_json['fields']}\")","key":"gJYH7OkSRp"},{"type":"output","id":"P7oPzlWUjkXmHv0dh90MO","data":[{"output_type":"stream","name":"stdout","text":"fields = ['date', 'energy', 'impact-e', 'lat', 'lat-dir', 'lon', 'lon-dir', 'alt', 'vel']\n"}],"key":"DZqvha6Ybu"}],"key":"VOWKrCtW9O"},{"type":"block","kind":"notebook-code","children":[{"type":"code","lang":"python","executable":true,"value":"# convert JSON data to a Pandas dataframe\nfireball_df = pd.DataFrame(fireball_json[\"data\"], columns=fireball_json[\"fields\"])\nfireball_df","key":"H5eaRT33T6"},{"type":"output","id":"jhgtI9rYjrjA_joXcLcH4","data":[{"output_type":"execute_result","execution_count":5,"metadata":{},"data":{"text/plain":{"content":"                    date energy impact-e   lat lat-dir    lon lon-dir   alt  \\\n0    2025-05-31 23:06:33   38.6        1  21.1       N   98.8       W  47.3   \n1    2025-04-28 15:01:15    3.4     0.12  45.1       S   67.3       E  31.4   \n2    2025-04-21 09:27:34    2.3    0.082  29.1       S  151.6       E  41.0   \n3    2025-04-08 14:16:48    2.1    0.076  32.2       S   10.4       E  44.9   \n4    2025-03-29 08:12:43    5.9     0.19  49.3       S   14.3       E  21.6   \n..                   ...    ...      ...   ...     ...    ...     ...   ...   \n414  2014-02-18 12:50:44    2.6    0.092  32.8       S   61.5       W  None   \n415  2014-02-13 06:47:42     63      1.5  13.3       N  110.7       W  25.0   \n416  2014-01-15 02:46:19   14.0     0.41  18.5       S  141.8       E  29.6   \n417  2014-01-12 16:00:48    7.8     0.24   2.9       N   64.4       E  37.0   \n418  2014-01-08 17:05:34    3.1     0.11   1.3       S  147.6       E  18.7   \n\n      vel  \n0    17.8  \n1    None  \n2    None  \n3    22.6  \n4    12.3  \n..    ...  \n414  None  \n415  None  \n416  None  \n417  16.2  \n418  44.8  \n\n[419 rows x 9 columns]","content_type":"text/plain"},"text/html":{"content":"<div>\n<style scoped>\n    .dataframe tbody tr th:only-of-type {\n        vertical-align: middle;\n    }\n\n    .dataframe tbody tr th {\n        vertical-align: top;\n    }\n\n    .dataframe thead th {\n        text-align: right;\n    }\n</style>\n<table border=\"1\" class=\"dataframe\">\n  <thead>\n    <tr style=\"text-align: right;\">\n      <th></th>\n      <th>date</th>\n      <th>energy</th>\n      <th>impact-e</th>\n      <th>lat</th>\n      <th>lat-dir</th>\n      <th>lon</th>\n      <th>lon-dir</th>\n      <th>alt</th>\n      <th>vel</th>\n    </tr>\n  </thead>\n  <tbody>\n    <tr>\n      <th>0</th>\n      <td>2025-05-31 23:06:33</td>\n      <td>38.6</td>\n      <td>1</td>\n      <td>21.1</td>\n      <td>N</td>\n      <td>98.8</td>\n      <td>W</td>\n      <td>47.3</td>\n      <td>17.8</td>\n    </tr>\n    <tr>\n      <th>1</th>\n      <td>2025-04-28 15:01:15</td>\n      <td>3.4</td>\n      <td>0.12</td>\n      <td>45.1</td>\n      <td>S</td>\n      <td>67.3</td>\n      <td>E</td>\n      <td>31.4</td>\n      <td>None</td>\n    </tr>\n    <tr>\n      <th>2</th>\n      <td>2025-04-21 09:27:34</td>\n      <td>2.3</td>\n      <td>0.082</td>\n      <td>29.1</td>\n      <td>S</td>\n      <td>151.6</td>\n      <td>E</td>\n      <td>41.0</td>\n      <td>None</td>\n    </tr>\n    <tr>\n      <th>3</th>\n      <td>2025-04-08 14:16:48</td>\n      <td>2.1</td>\n      <td>0.076</td>\n      <td>32.2</td>\n      <td>S</td>\n      <td>10.4</td>\n      <td>E</td>\n      <td>44.9</td>\n      <td>22.6</td>\n    </tr>\n    <tr>\n      <th>4</th>\n      <td>2025-03-29 08:12:43</td>\n      <td>5.9</td>\n      <td>0.19</td>\n      <td>49.3</td>\n      <td>S</td>\n      <td>14.3</td>\n      <td>E</td>\n      <td>21.6</td>\n      <td>12.3</td>\n    </tr>\n    <tr>\n      <th>...</th>\n      <td>...</td>\n      <td>...</td>\n      <td>...</td>\n      <td>...</td>\n      <td>...</td>\n      <td>...</td>\n      <td>...</td>\n      <td>...</td>\n      <td>...</td>\n    </tr>\n    <tr>\n      <th>414</th>\n      <td>2014-02-18 12:50:44</td>\n      <td>2.6</td>\n      <td>0.092</td>\n      <td>32.8</td>\n      <td>S</td>\n      <td>61.5</td>\n      <td>W</td>\n      <td>None</td>\n      <td>None</td>\n    </tr>\n    <tr>\n      <th>415</th>\n      <td>2014-02-13 06:47:42</td>\n      <td>63</td>\n      <td>1.5</td>\n      <td>13.3</td>\n      <td>N</td>\n      <td>110.7</td>\n      <td>W</td>\n      <td>25.0</td>\n      <td>None</td>\n    </tr>\n    <tr>\n      <th>416</th>\n      <td>2014-01-15 02:46:19</td>\n      <td>14.0</td>\n      <td>0.41</td>\n      <td>18.5</td>\n      <td>S</td>\n      <td>141.8</td>\n      <td>E</td>\n      <td>29.6</td>\n      <td>None</td>\n    </tr>\n    <tr>\n      <th>417</th>\n      <td>2014-01-12 16:00:48</td>\n      <td>7.8</td>\n      <td>0.24</td>\n      <td>2.9</td>\n      <td>N</td>\n      <td>64.4</td>\n      <td>E</td>\n      <td>37.0</td>\n      <td>16.2</td>\n    </tr>\n    <tr>\n      <th>418</th>\n      <td>2014-01-08 17:05:34</td>\n      <td>3.1</td>\n      <td>0.11</td>\n      <td>1.3</td>\n      <td>S</td>\n      <td>147.6</td>\n      <td>E</td>\n      <td>18.7</td>\n      <td>44.8</td>\n    </tr>\n  </tbody>\n</table>\n<p>419 rows × 9 columns</p>\n</div>","content_type":"text/html"}}}],"key":"FCjk9SQ0Mn"}],"key":"sBEmc6ve7P"},{"type":"block","kind":"notebook-code","children":[{"type":"code","lang":"python","executable":true,"value":"# remove nan and duplicated data rows and reindex rows\nfireball_df.dropna(inplace=True, ignore_index=True)\n\n# convert columnss from strings to a float\nfireball_df[\"energy\"] = fireball_df[\"energy\"].astype(float)\nfireball_df[\"impact-e\"] = fireball_df[\"impact-e\"].astype(float)\nfireball_df[\"lat\"] = fireball_df[\"lat\"].astype(float)\nfireball_df[\"lon\"] = fireball_df[\"lon\"].astype(float)\nfireball_df[\"alt\"] = fireball_df[\"alt\"].astype(float)\nfireball_df[\"vel\"] = fireball_df[\"vel\"].astype(float)\n\n# convert latitude to negative if lat-dir is S and longitude to negative if lon-dir is W\nfireball_df['lat'] = fireball_df['lat'].mask(fireball_df['lat-dir'].eq('S'), -fireball_df['lat'])\nfireball_df['lon'] = fireball_df['lon'].mask(fireball_df['lon-dir'].eq('W'), -fireball_df['lon'])\n\n# rename columns\nfireball_df = fireball_df.rename(columns= {\"impact-e\": \"impact energy\",\n                                           \"lat\": \"latitude\",\n                                           \"lat-dir\": \"latitude direction\",\n                                           \"lon\": \"longitude\",\n                                           \"lon-dir\": \"longitude direction\",\n                                           \"alt\": \"altitude\",\n                                           \"vel\": \"velocity\"})\n\n\nfireball_df","key":"KP9lRa2iux"},{"type":"output","id":"sH-qBMNWwmlw7FDR0rgPU","data":[{"output_type":"execute_result","execution_count":6,"metadata":{},"data":{"text/plain":{"content":"                    date  energy  impact energy  latitude latitude direction  \\\n0    2025-05-31 23:06:33    38.6          1.000      21.1                  N   \n1    2025-04-08 14:16:48     2.1          0.076     -32.2                  S   \n2    2025-03-29 08:12:43     5.9          0.190     -49.3                  S   \n3    2025-03-27 16:05:23   104.5          2.400      14.3                  N   \n4    2025-03-24 05:51:43     4.9          0.160     -70.4                  S   \n..                   ...     ...            ...       ...                ...   \n235  2014-05-16 12:42:48    30.9          0.820     -44.2                  S   \n236  2014-05-08 19:42:37   105.0          2.400     -36.9                  S   \n237  2014-03-29 13:45:41     3.9          0.130     -28.7                  S   \n238  2014-01-12 16:00:48     7.8          0.240       2.9                  N   \n239  2014-01-08 17:05:34     3.1          0.110      -1.3                  S   \n\n     longitude longitude direction  altitude  velocity  \n0        -98.8                   W      47.3      17.8  \n1         10.4                   E      44.9      22.6  \n2         14.3                   E      21.6      12.3  \n3       -111.5                   W      38.1      21.3  \n4        114.2                   E      21.5      28.2  \n..         ...                 ...       ...       ...  \n235     -176.2                   W      44.0      16.5  \n236       87.3                   E      35.4      19.0  \n237      121.5                   E      30.7      16.3  \n238       64.4                   E      37.0      16.2  \n239      147.6                   E      18.7      44.8  \n\n[240 rows x 9 columns]","content_type":"text/plain"},"text/html":{"content":"<div>\n<style scoped>\n    .dataframe tbody tr th:only-of-type {\n        vertical-align: middle;\n    }\n\n    .dataframe tbody tr th {\n        vertical-align: top;\n    }\n\n    .dataframe thead th {\n        text-align: right;\n    }\n</style>\n<table border=\"1\" class=\"dataframe\">\n  <thead>\n    <tr style=\"text-align: right;\">\n      <th></th>\n      <th>date</th>\n      <th>energy</th>\n      <th>impact energy</th>\n      <th>latitude</th>\n      <th>latitude direction</th>\n      <th>longitude</th>\n      <th>longitude direction</th>\n      <th>altitude</th>\n      <th>velocity</th>\n    </tr>\n  </thead>\n  <tbody>\n    <tr>\n      <th>0</th>\n      <td>2025-05-31 23:06:33</td>\n      <td>38.6</td>\n      <td>1.000</td>\n      <td>21.1</td>\n      <td>N</td>\n      <td>-98.8</td>\n      <td>W</td>\n      <td>47.3</td>\n      <td>17.8</td>\n    </tr>\n    <tr>\n      <th>1</th>\n      <td>2025-04-08 14:16:48</td>\n      <td>2.1</td>\n      <td>0.076</td>\n      <td>-32.2</td>\n      <td>S</td>\n      <td>10.4</td>\n      <td>E</td>\n      <td>44.9</td>\n      <td>22.6</td>\n    </tr>\n    <tr>\n      <th>2</th>\n      <td>2025-03-29 08:12:43</td>\n      <td>5.9</td>\n      <td>0.190</td>\n      <td>-49.3</td>\n      <td>S</td>\n      <td>14.3</td>\n      <td>E</td>\n      <td>21.6</td>\n      <td>12.3</td>\n    </tr>\n    <tr>\n      <th>3</th>\n      <td>2025-03-27 16:05:23</td>\n      <td>104.5</td>\n      <td>2.400</td>\n      <td>14.3</td>\n      <td>N</td>\n      <td>-111.5</td>\n      <td>W</td>\n      <td>38.1</td>\n      <td>21.3</td>\n    </tr>\n    <tr>\n      <th>4</th>\n      <td>2025-03-24 05:51:43</td>\n      <td>4.9</td>\n      <td>0.160</td>\n      <td>-70.4</td>\n      <td>S</td>\n      <td>114.2</td>\n      <td>E</td>\n      <td>21.5</td>\n      <td>28.2</td>\n    </tr>\n    <tr>\n      <th>...</th>\n      <td>...</td>\n      <td>...</td>\n      <td>...</td>\n      <td>...</td>\n      <td>...</td>\n      <td>...</td>\n      <td>...</td>\n      <td>...</td>\n      <td>...</td>\n    </tr>\n    <tr>\n      <th>235</th>\n      <td>2014-05-16 12:42:48</td>\n      <td>30.9</td>\n      <td>0.820</td>\n      <td>-44.2</td>\n      <td>S</td>\n      <td>-176.2</td>\n      <td>W</td>\n      <td>44.0</td>\n      <td>16.5</td>\n    </tr>\n    <tr>\n      <th>236</th>\n      <td>2014-05-08 19:42:37</td>\n      <td>105.0</td>\n      <td>2.400</td>\n      <td>-36.9</td>\n      <td>S</td>\n      <td>87.3</td>\n      <td>E</td>\n      <td>35.4</td>\n      <td>19.0</td>\n    </tr>\n    <tr>\n      <th>237</th>\n      <td>2014-03-29 13:45:41</td>\n      <td>3.9</td>\n      <td>0.130</td>\n      <td>-28.7</td>\n      <td>S</td>\n      <td>121.5</td>\n      <td>E</td>\n      <td>30.7</td>\n      <td>16.3</td>\n    </tr>\n    <tr>\n      <th>238</th>\n      <td>2014-01-12 16:00:48</td>\n      <td>7.8</td>\n      <td>0.240</td>\n      <td>2.9</td>\n      <td>N</td>\n      <td>64.4</td>\n      <td>E</td>\n      <td>37.0</td>\n      <td>16.2</td>\n    </tr>\n    <tr>\n      <th>239</th>\n      <td>2014-01-08 17:05:34</td>\n      <td>3.1</td>\n      <td>0.110</td>\n      <td>-1.3</td>\n      <td>S</td>\n      <td>147.6</td>\n      <td>E</td>\n      <td>18.7</td>\n      <td>44.8</td>\n    </tr>\n  </tbody>\n</table>\n<p>240 rows × 9 columns</p>\n</div>","content_type":"text/html"}}}],"key":"QdHQAir5TB"}],"key":"kNNxAfoxai"},{"type":"block","kind":"notebook-code","children":[{"type":"code","lang":"python","executable":true,"value":"fireball_df.info()","key":"GxqDQzkLOa"},{"type":"output","id":"-uiA4mlxxHwc8bTHCGjj0","data":[{"output_type":"stream","name":"stdout","text":"<class 'pandas.core.frame.DataFrame'>\nRangeIndex: 240 entries, 0 to 239\nData columns (total 9 columns):\n #   Column               Non-Null Count  Dtype  \n---  ------               --------------  -----  \n 0   date                 240 non-null    object \n 1   energy               240 non-null    float64\n 2   impact energy        240 non-null    float64\n 3   latitude             240 non-null    float64\n 4   latitude direction   240 non-null    object \n 5   longitude            240 non-null    float64\n 6   longitude direction  240 non-null    object \n 7   altitude             240 non-null    float64\n 8   velocity             240 non-null    float64\ndtypes: float64(6), object(3)\nmemory usage: 17.0+ KB\n"}],"key":"AOyh6WlOEg"}],"key":"dYSVzfJ6Lw"},{"type":"block","kind":"notebook-content","children":[{"type":"heading","depth":3,"position":{"start":{"line":1,"column":1},"end":{"line":1,"column":1}},"children":[{"type":"text","value":"Plot the Energy of Fireballs","position":{"start":{"line":1,"column":1},"end":{"line":1,"column":1}},"key":"wD4ToTDt8D"}],"identifier":"plot-the-energy-of-fireballs","label":"Plot the Energy of Fireballs","html_id":"plot-the-energy-of-fireballs","implicit":true,"key":"mEM35jYndF"}],"key":"r4Khl54eLP"},{"type":"block","kind":"notebook-code","children":[{"type":"code","lang":"python","executable":true,"value":"# retrieve world map from GeoPandas\nworld_map = geopandas.read_file(geopandas.datasets.get_path(\"naturalearth_lowres\"))\n\n# Set up world map plot\nfig, ax = plt.subplots(figsize=(15, 10))\nworld_map.plot(color=\"grey\", ax=ax)\n\n# Plot Fireball Locations with Energy\nx = fireball_df[\"longitude\"]\ny = fireball_df[\"latitude\"]\nz = fireball_df[\"energy\"]\nplt.scatter(x, y, s=5*z, c=z, cmap=\"autumn\")\nplt.colorbar(label=\"Approximate Total Radiated Energy (10^10 Joules)\")\n\n# Setup Axis Limits and Title/Labels\nplt.xlim([-180, 180])\nplt.ylim([-90, 90])\nplt.title(\"Energy of Fireball Observations\")\nplt.xlabel(\"Longitude (Degrees)\")\nplt.ylabel(\"Latitude (Degrees)\")\nplt.show()","key":"LfdLsIKQrH"},{"type":"output","id":"kdKRzctRXj-vh-nFzWz-C","data":[{"output_type":"error","traceback":"\u001b[31m---------------------------------------------------------------------------\u001b[39m\n\u001b[31mAttributeError\u001b[39m                            Traceback (most recent call last)\n\u001b[36mCell\u001b[39m\u001b[36m \u001b[39m\u001b[32mIn[8]\u001b[39m\u001b[32m, line 2\u001b[39m\n\u001b[32m      1\u001b[39m \u001b[38;5;66;03m# retrieve world map from GeoPandas\u001b[39;00m\n\u001b[32m----> \u001b[39m\u001b[32m2\u001b[39m world_map = geopandas.read_file(\u001b[43mgeopandas\u001b[49m\u001b[43m.\u001b[49m\u001b[43mdatasets\u001b[49m\u001b[43m.\u001b[49m\u001b[43mget_path\u001b[49m\u001b[43m(\u001b[49m\u001b[33;43m\"\u001b[39;49m\u001b[33;43mnaturalearth_lowres\u001b[39;49m\u001b[33;43m\"\u001b[39;49m\u001b[43m)\u001b[49m)\n\u001b[32m      4\u001b[39m \u001b[38;5;66;03m# Set up world map plot\u001b[39;00m\n\u001b[32m      5\u001b[39m fig, ax = plt.subplots(figsize=(\u001b[32m15\u001b[39m, \u001b[32m10\u001b[39m))\n\n\u001b[36mFile \u001b[39m\u001b[32m~/micromamba/envs/api-cookbook-dev/lib/python3.13/site-packages/geopandas/datasets/__init__.py:18\u001b[39m, in \u001b[36mget_path\u001b[39m\u001b[34m(dataset)\u001b[39m\n\u001b[32m     12\u001b[39m error_msg = (\n\u001b[32m     13\u001b[39m     \u001b[33m\"\u001b[39m\u001b[33mThe geopandas.dataset has been deprecated and was removed in GeoPandas \u001b[39m\u001b[33m\"\u001b[39m\n\u001b[32m     14\u001b[39m     \u001b[33mf\u001b[39m\u001b[33m\"\u001b[39m\u001b[33m1.0. You can get the original \u001b[39m\u001b[33m'\u001b[39m\u001b[38;5;132;01m{\u001b[39;00mdataset\u001b[38;5;132;01m}\u001b[39;00m\u001b[33m'\u001b[39m\u001b[33m data from \u001b[39m\u001b[33m\"\u001b[39m\n\u001b[32m     15\u001b[39m     \u001b[33mf\u001b[39m\u001b[33m\"\u001b[39m\u001b[38;5;132;01m{\u001b[39;00mne_message\u001b[38;5;250m \u001b[39m\u001b[38;5;28;01mif\u001b[39;00m\u001b[38;5;250m \u001b[39m\u001b[33m'\u001b[39m\u001b[33mnatural\u001b[39m\u001b[33m'\u001b[39m\u001b[38;5;250m \u001b[39m\u001b[38;5;129;01min\u001b[39;00m\u001b[38;5;250m \u001b[39mdataset\u001b[38;5;250m \u001b[39m\u001b[38;5;28;01melse\u001b[39;00m\u001b[38;5;250m \u001b[39mnybb_message\u001b[38;5;132;01m}\u001b[39;00m\u001b[33m\"\u001b[39m\n\u001b[32m     16\u001b[39m )\n\u001b[32m     17\u001b[39m \u001b[38;5;28;01mif\u001b[39;00m dataset \u001b[38;5;129;01min\u001b[39;00m _prev_available:\n\u001b[32m---> \u001b[39m\u001b[32m18\u001b[39m     \u001b[38;5;28;01mraise\u001b[39;00m \u001b[38;5;167;01mAttributeError\u001b[39;00m(error_msg)\n\u001b[32m     19\u001b[39m \u001b[38;5;28;01melse\u001b[39;00m:\n\u001b[32m     20\u001b[39m     error_msg = (\n\u001b[32m     21\u001b[39m         \u001b[33m\"\u001b[39m\u001b[33mThe geopandas.dataset has been deprecated and \u001b[39m\u001b[33m\"\u001b[39m\n\u001b[32m     22\u001b[39m         \u001b[33m\"\u001b[39m\u001b[33mwas removed in GeoPandas 1.0. New sample datasets are now available \u001b[39m\u001b[33m\"\u001b[39m\n\u001b[32m     23\u001b[39m         \u001b[33m\"\u001b[39m\u001b[33min the geodatasets package (https://geodatasets.readthedocs.io/en/latest/)\u001b[39m\u001b[33m\"\u001b[39m\n\u001b[32m     24\u001b[39m     )\n\n\u001b[31mAttributeError\u001b[39m: The geopandas.dataset has been deprecated and was removed in GeoPandas 1.0. You can get the original 'naturalearth_lowres' data from https://www.naturalearthdata.com/downloads/110m-cultural-vectors/.","ename":"AttributeError","evalue":"The geopandas.dataset has been deprecated and was removed in GeoPandas 1.0. You can get the original 'naturalearth_lowres' data from https://www.naturalearthdata.com/downloads/110m-cultural-vectors/."}],"key":"U9FvtBnLzf"}],"key":"mzXoiKnDaL"},{"type":"block","kind":"notebook-content","children":[{"type":"heading","depth":3,"position":{"start":{"line":1,"column":1},"end":{"line":1,"column":1}},"children":[{"type":"text","value":"Plot the Impact Energy of Fireballs","position":{"start":{"line":1,"column":1},"end":{"line":1,"column":1}},"key":"DYWZAjXamB"}],"identifier":"plot-the-impact-energy-of-fireballs","label":"Plot the Impact Energy of Fireballs","html_id":"plot-the-impact-energy-of-fireballs","implicit":true,"key":"hN3QAM8Ukb"}],"key":"nF5AbrP5ru"},{"type":"block","kind":"notebook-code","children":[{"type":"code","lang":"python","executable":true,"value":"# retrieve world map from GeoPandas\nworld_map = geopandas.read_file(geopandas.datasets.get_path(\"naturalearth_lowres\"))\n\n# Set up world map plot\nfig, ax = plt.subplots(figsize=(15, 10))\nworld_map.plot(color=\"grey\", ax=ax)\n\n# Plot Fireball Locations with Energy\nx = fireball_df[\"longitude\"]\ny = fireball_df[\"latitude\"]\nz = fireball_df[\"impact energy\"]\nplt.scatter(x, y, s=5*z, c=z, cmap=\"autumn\")\nplt.colorbar(label=\"Approximate Total Impact Energy (kt)\")\n\n# Setup Axis Limits and Title/Labels\nplt.xlim([-180, 180])\nplt.ylim([-90, 90])\nplt.title(\"Total Impact Energy of Fireball Observations\")\nplt.xlabel(\"Longitude (Degrees)\")\nplt.ylabel(\"Latitude (Degrees)\")\nplt.show()","key":"HxKlrvW8hX"},{"type":"output","id":"9RoF3_x1UVLOiIbZud_3a","data":[],"key":"k0S6tyex2M"}],"key":"enZ9qli9G5"},{"type":"block","kind":"notebook-content","children":[{"type":"heading","depth":3,"position":{"start":{"line":1,"column":1},"end":{"line":1,"column":1}},"children":[{"type":"text","value":"Plot the Velocity of Fireballs","position":{"start":{"line":1,"column":1},"end":{"line":1,"column":1}},"key":"A1PjelosJI"}],"identifier":"plot-the-velocity-of-fireballs","label":"Plot the Velocity of Fireballs","html_id":"plot-the-velocity-of-fireballs","implicit":true,"key":"tGyKh7tT9w"}],"key":"GpeNpaX2h0"},{"type":"block","kind":"notebook-code","children":[{"type":"code","lang":"python","executable":true,"value":"# retrieve world map from GeoPandas\nworld_map = geopandas.read_file(geopandas.datasets.get_path(\"naturalearth_lowres\"))\n\n# Set up world map plot\nfig, ax = plt.subplots(figsize=(15, 10))\nworld_map.plot(color=\"grey\", ax=ax)\n\n# Plot Fireball Locations with Velocity\nx = fireball_df[\"longitude\"]\ny = fireball_df[\"latitude\"]\nz = fireball_df[\"velocity\"]\nplt.scatter(x, y, s=5*z, c=z, cmap=\"winter\")\nplt.colorbar(label=\"Pre-Entry Velocity (km/s)\")\n\n# Setup Axis Limits and Title/Labels\nplt.xlim([-180, 180])\nplt.ylim([-90, 90])\nplt.title(\"Pre-Entry Velocity of Fireball Observations\")\nplt.xlabel(\"Longitude (Degrees)\")\nplt.ylabel(\"Latitude (Degrees)\")\nplt.show()","key":"lAsTVUHWz3"},{"type":"output","id":"eo9UCsGdMG5OKkfIE3UyS","data":[],"key":"SDDipEVcdC"}],"key":"yvD4zjXw6z"},{"type":"block","kind":"notebook-content","children":[{"type":"heading","depth":3,"position":{"start":{"line":1,"column":1},"end":{"line":1,"column":1}},"children":[{"type":"text","value":"Plot the Altitude of Fireballs","position":{"start":{"line":1,"column":1},"end":{"line":1,"column":1}},"key":"FiHwX5GlO7"}],"identifier":"plot-the-altitude-of-fireballs","label":"Plot the Altitude of Fireballs","html_id":"plot-the-altitude-of-fireballs","implicit":true,"key":"FpnEHGw4K2"}],"key":"KLc9lEVc1z"},{"type":"block","kind":"notebook-code","children":[{"type":"code","lang":"python","executable":true,"value":"# retrieve world map from GeoPandas\nworld_map = geopandas.read_file(geopandas.datasets.get_path(\"naturalearth_lowres\"))\n\n# Set up world map plot\nfig, ax = plt.subplots(figsize=(15, 10))\nworld_map.plot(color=\"grey\", ax=ax)\n\n# Plot Fireball Locations with Energy\nx = fireball_df[\"longitude\"]\ny = fireball_df[\"latitude\"]\nz = fireball_df[\"altitude\"]\nplt.scatter(x, y, s=5*z, c=z, cmap=\"bone\")\nplt.colorbar(label=\"Altitude Above Geoid at Peak Brightness (km)\")\n\n# Setup Axis Limits and Title/Labels\nplt.xlim([-180, 180])\nplt.ylim([-90, 90])\nplt.title(\"Altitude of Fireball Observations\")\nplt.xlabel(\"Longitude (Degrees)\")\nplt.ylabel(\"Latitude (Degrees)\")\nplt.show()","key":"OnpxT1ihyD"},{"type":"output","id":"l9zXlKiUoUUeb_k9c9RIO","data":[],"key":"v7OGHtVoQn"}],"key":"QCmlRrmjx2"},{"type":"block","kind":"notebook-content","children":[{"type":"heading","depth":2,"position":{"start":{"line":1,"column":1},"end":{"line":1,"column":1}},"children":[{"type":"text","value":"Last Section","position":{"start":{"line":1,"column":1},"end":{"line":1,"column":1}},"key":"PPUGOnCOzE"}],"identifier":"last-section","label":"Last Section","html_id":"last-section","implicit":true,"key":"Y7IFIxY04A"},{"type":"paragraph","position":{"start":{"line":3,"column":1},"end":{"line":3,"column":1}},"children":[{"type":"text","value":"If you’re comfortable, and as we briefly used for our embedded logo up top, you can embed raw html into Jupyter Markdown cells (edit to see):","position":{"start":{"line":3,"column":1},"end":{"line":3,"column":1}},"key":"oZSV2ntzTO"}],"key":"Di0Tj3H5KG"}],"key":"WJtYKmjeE6"},{"type":"block","kind":"notebook-content","children":[{"type":"div","class":"admonition alert alert-info","children":[{"type":"paragraph","children":[{"type":"text","value":"Info","key":"CeNRSpN8Oq"}],"key":"V0V2ULfM3S"},{"type":"text","value":"Your relevant information here!","key":"PhnZjZsarm"}],"key":"QvuxM67Wnk"}],"key":"wnE25zkcPX"},{"type":"block","kind":"notebook-content","children":[{"type":"paragraph","position":{"start":{"line":1,"column":1},"end":{"line":1,"column":1}},"children":[{"type":"text","value":"Feel free to copy this around and edit or play around with yourself. Some other ","position":{"start":{"line":1,"column":1},"end":{"line":1,"column":1}},"key":"tBXrntRqNT"},{"type":"inlineCode","value":"admonitions","position":{"start":{"line":1,"column":1},"end":{"line":1,"column":1}},"key":"ui2Bw5jqDk"},{"type":"text","value":" you can put in:","position":{"start":{"line":1,"column":1},"end":{"line":1,"column":1}},"key":"Onzlxg5sry"}],"key":"doNnGuT7r6"}],"key":"YKRxTqiFCY"},{"type":"block","kind":"notebook-content","children":[{"type":"div","class":"admonition alert alert-success","children":[{"type":"paragraph","children":[{"type":"text","value":"Success","key":"K7MuhVpk7s"}],"key":"Yml6NtZRUU"},{"type":"text","value":"We got this done after all!","key":"k0sIZiu6un"}],"key":"s0ci0L3EKA"}],"key":"WjKtgZFuth"},{"type":"block","kind":"notebook-content","children":[{"type":"div","class":"admonition alert alert-warning","children":[{"type":"paragraph","children":[{"type":"text","value":"Warning","key":"htdsgJuCu4"}],"key":"y3hYayc3sS"},{"type":"text","value":"Be careful!","key":"VXIN0OkR5z"}],"key":"rri48L2L7v"}],"key":"Q8juVgRisH"},{"type":"block","kind":"notebook-content","children":[{"type":"div","class":"admonition alert alert-danger","children":[{"type":"paragraph","children":[{"type":"text","value":"Danger","key":"zUaDVq0ri6"}],"key":"yJycJllvbH"},{"type":"text","value":"Scary stuff be here.","key":"MOMoEt6bwF"}],"key":"Fr38T9pG4T"}],"key":"yQ7Dy1oZTV"},{"type":"block","kind":"notebook-content","children":[{"type":"paragraph","position":{"start":{"line":1,"column":1},"end":{"line":1,"column":1}},"children":[{"type":"text","value":"We also suggest checking out Jupyter Book’s ","position":{"start":{"line":1,"column":1},"end":{"line":1,"column":1}},"key":"IhRiceaNzf"},{"type":"link","url":"https://jupyterbook.org/content/metadata.html#jupyter-cell-tags","position":{"start":{"line":1,"column":1},"end":{"line":1,"column":1}},"children":[{"type":"text","value":"brief demonstration","position":{"start":{"line":1,"column":1},"end":{"line":1,"column":1}},"key":"pQlgswy0dk"}],"urlSource":"https://jupyterbook.org/content/metadata.html#jupyter-cell-tags","key":"oYO9Nj85Jm"},{"type":"text","value":" on adding cell tags to your cells in Jupyter Notebook, Lab, or manually. Using these cell tags can allow you to ","position":{"start":{"line":1,"column":1},"end":{"line":1,"column":1}},"key":"Fdjguqj6iF"},{"type":"link","url":"https://jupyterbook.org/interactive/hiding.html","position":{"start":{"line":1,"column":1},"end":{"line":1,"column":1}},"children":[{"type":"text","value":"customize","position":{"start":{"line":1,"column":1},"end":{"line":1,"column":1}},"key":"hwdjq3Bif4"}],"urlSource":"https://jupyterbook.org/interactive/hiding.html","key":"YxCH8VwEme"},{"type":"text","value":" how your code content is displayed and even ","position":{"start":{"line":1,"column":1},"end":{"line":1,"column":1}},"key":"JbsOW3C8Z9"},{"type":"link","url":"https://jupyterbook.org/content/execute.html#dealing-with-code-that-raises-errors","position":{"start":{"line":1,"column":1},"end":{"line":1,"column":1}},"children":[{"type":"text","value":"demonstrate errors","position":{"start":{"line":1,"column":1},"end":{"line":1,"column":1}},"key":"N6D4e3BWu9"}],"urlSource":"https://jupyterbook.org/content/execute.html#dealing-with-code-that-raises-errors","key":"KONsYmYuJV"},{"type":"text","value":" without altogether crashing our loyal army of machines!","position":{"start":{"line":1,"column":1},"end":{"line":1,"column":1}},"key":"WrPfaNSniX"}],"key":"bMhJqhCIv4"}],"key":"IFN6fzAU5N"},{"type":"block","kind":"notebook-content","children":[{"type":"thematicBreak","position":{"start":{"line":1,"column":1},"end":{"line":1,"column":1}},"key":"JpbNZBpig9"}],"key":"J5lMc3aOaS"},{"type":"block","kind":"notebook-content","children":[{"type":"heading","depth":2,"position":{"start":{"line":1,"column":1},"end":{"line":1,"column":1}},"children":[{"type":"text","value":"Summary","position":{"start":{"line":1,"column":1},"end":{"line":1,"column":1}},"key":"Va9ACmu5w0"}],"identifier":"summary","label":"Summary","html_id":"summary","implicit":true,"key":"uggcqI4XIV"},{"type":"paragraph","position":{"start":{"line":2,"column":1},"end":{"line":2,"column":1}},"children":[{"type":"text","value":"Add one final ","position":{"start":{"line":2,"column":1},"end":{"line":2,"column":1}},"key":"ubozlru1VQ"},{"type":"inlineCode","value":"---","position":{"start":{"line":2,"column":1},"end":{"line":2,"column":1}},"key":"A33QZMhdq3"},{"type":"text","value":" marking the end of your body of content, and then conclude with a brief single paragraph summarizing at a high level the key pieces that were learned and how they tied to your objectives. Look to reiterate what the most important takeaways were.","position":{"start":{"line":2,"column":1},"end":{"line":2,"column":1}},"key":"ncn502aVia"}],"key":"snUfwf67ta"},{"type":"heading","depth":3,"position":{"start":{"line":4,"column":1},"end":{"line":4,"column":1}},"children":[{"type":"text","value":"What’s next?","position":{"start":{"line":4,"column":1},"end":{"line":4,"column":1}},"key":"xinlfbu6Pv"}],"identifier":"whats-next","label":"What’s next?","html_id":"whats-next","implicit":true,"key":"Gd8QEoiWGK"},{"type":"paragraph","position":{"start":{"line":5,"column":1},"end":{"line":5,"column":1}},"children":[{"type":"text","value":"Let Jupyter book tie this to the next (sequential) piece of content that people could move on to down below and in the sidebar. However, if this page uniquely enables your reader to tackle other nonsequential concepts throughout this book, or even external content, link to it here!","position":{"start":{"line":5,"column":1},"end":{"line":5,"column":1}},"key":"L43cPyxen5"}],"key":"X1mEQczIW8"}],"key":"Cwap017zf2"},{"type":"block","kind":"notebook-content","children":[{"type":"heading","depth":2,"position":{"start":{"line":1,"column":1},"end":{"line":1,"column":1}},"children":[{"type":"text","value":"Resources and references","position":{"start":{"line":1,"column":1},"end":{"line":1,"column":1}},"key":"EP1lU4b8Pj"}],"identifier":"resources-and-references","label":"Resources and references","html_id":"resources-and-references","implicit":true,"key":"P0BfC1ETlv"},{"type":"list","ordered":false,"spread":false,"position":{"start":{"line":3,"column":1},"end":{"line":3,"column":1}},"children":[{"type":"listItem","spread":true,"position":{"start":{"line":3,"column":1},"end":{"line":3,"column":1}},"children":[{"type":"text","value":"More information about ","position":{"start":{"line":3,"column":1},"end":{"line":3,"column":1}},"key":"RvHaP891qM"},{"type":"link","url":"https://medium.com/@kavee625/plotting-data-on-the-world-map-with-geopandas-f03742615196","position":{"start":{"line":3,"column":1},"end":{"line":3,"column":1}},"children":[{"type":"text","value":"plotting a world map with GeoPandas","position":{"start":{"line":3,"column":1},"end":{"line":3,"column":1}},"key":"wPEvGlw0Tm"}],"urlSource":"https://medium.com/@kavee625/plotting-data-on-the-world-map-with-geopandas-f03742615196","key":"wtLSfzG4r6"}],"key":"MYP3iaQFLJ"}],"key":"s8l92ehTBp"}],"key":"VA65KLPpVP"}],"key":"Uw1boz2cBE"},"references":{"cite":{"order":[],"data":{}}},"footer":{"navigation":{"prev":{"title":"Visualizing Data with EPA’s Air Quality System (AQS) API","url":"/notebooks/example-workflows/air-quality-system-api","group":"Example Workflows"},"next":{"title":"Data access via earthaccess library and vizualization with cartopy","url":"/notebooks/example-workflows/earthaccess-sla-sss","group":"Example Workflows"}}},"domain":"http://localhost:3000"}